wandbfs/__init__.py
wandbfs/_wandbfs.py
wandbfs-0.0.2.dist-info/LICENSE
wandbfs-0.0.2.dist-info/METADATA
wandbfs-0.0.2.dist-info/WHEEL
wandbfs-0.0.2.dist-info/entry_points.txt
wandbfs-0.0.2.dist-info/top_level.txt
wandbfs-0.0.2.dist-info/RECORD
