Metadata-Version: 2.1
Name: wandbfs
Version: 0.0.2
Summary: UNKNOWN
Home-page: https://github.com/jkulhanek/wandbfs
Author: Jonáš Kulhánek
Author-email: jonas.kulhanek@live.com
License: MIT License
Platform: UNKNOWN
Requires-Dist: wandb (>=0.8.32)
Requires-Dist: fsspec (>=0.9.0)
